auxknow/__init__.py
auxknow/version.py
auxknow/ai/__init__.py
auxknow/ai/llm_adapter.py
auxknow/common/__init__.py
auxknow/common/constants.py
auxknow/common/custom_errors.py
auxknow/common/llm_factory.py
auxknow/common/models.py
auxknow/common/performance.py
auxknow/common/printer.py
auxknow/common/stream_processor.py
auxknow/engine/__init__.py
auxknow/engine/auxknow.py
auxknow/engine/auxknow_config.py
auxknow/engine/auxknow_memory.py
auxknow/engine/auxknow_search.py
e2e/__init__.py
e2e/test_basic_flow.py
e2e/helpers/__init__.py
e2e/helpers/mock_llm_factory.py
auxknow-0.0.20.dist-info/LICENSE
auxknow-0.0.20.dist-info/METADATA
auxknow-0.0.20.dist-info/WHEEL
auxknow-0.0.20.dist-info/top_level.txt
auxknow-0.0.20.dist-info/RECORD
